py_crypto/__init__.py
py_crypto/config.py
py_crypto/crypto.py
py_crypto/kms.py
pycryptokms-0.1.1.dist-info/LICENCE
pycryptokms-0.1.1.dist-info/METADATA
pycryptokms-0.1.1.dist-info/NOTICE
pycryptokms-0.1.1.dist-info/WHEEL
pycryptokms-0.1.1.dist-info/top_level.txt
pycryptokms-0.1.1.dist-info/RECORD
